DESCRIPTION.txt
EMAIL.txt
HISTORY.txt
LICENSE.txt
MANIFEST.in
NEWS.txt
NEWS_DEV.txt
README.rst
requirements-rtd.txt
requirements.txt
setup.cfg
setup.py
versioneer.py
Theano_PyMC.egg-info/PKG-INFO
Theano_PyMC.egg-info/SOURCES.txt
Theano_PyMC.egg-info/dependency_links.txt
Theano_PyMC.egg-info/entry_points.txt
Theano_PyMC.egg-info/requires.txt
Theano_PyMC.egg-info/top_level.txt
bin/__init__.py
bin/theano-cache
bin/theano_cache.py
doc/LICENSE.txt
doc/NEWS.txt
doc/acknowledgement.txt
doc/citation.txt
doc/core_development_guide.txt
doc/dev_start_guide.txt
doc/faq.txt
doc/glossary.txt
doc/index.txt
doc/install.txt
doc/install_centos6.txt
doc/install_macos.txt
doc/install_others.txt
doc/install_ubuntu.txt
doc/install_windows.txt
doc/introduction.txt
doc/links.txt
doc/nice_quotes.txt
doc/optimizations.txt
doc/requirements.txt
doc/troubleshooting.txt
doc/updating.txt
doc/cifarSC2011/advanced_theano.txt
doc/cifarSC2011/boot_camp_overview.txt
doc/cifarSC2011/gpundarray.txt
doc/cifarSC2011/index.txt
doc/cifarSC2011/introduction.txt
doc/cifarSC2011/pyCUDA.txt
doc/cifarSC2011/theano.txt
doc/crei2013/advanced_theano.txt
doc/crei2013/gpundarray.txt
doc/crei2013/index.txt
doc/crei2013/introduction.txt
doc/crei2013/theano.txt
doc/extending/cop.txt
doc/extending/ctype.txt
doc/extending/extending_faq.txt
doc/extending/extending_theano.txt
doc/extending/extending_theano_c.txt
doc/extending/extending_theano_gpu.txt
doc/extending/fibby.txt
doc/extending/graphstructures.txt
doc/extending/index.txt
doc/extending/inplace.txt
doc/extending/op.txt
doc/extending/optimization.txt
doc/extending/other_ops.txt
doc/extending/pipeline.txt
doc/extending/scan.txt
doc/extending/theano_vs_c.txt
doc/extending/tips.txt
doc/extending/type.txt
doc/extending/unittest.txt
doc/extending/using_params.txt
doc/internal/dev_start_guide.txt
doc/internal/how_to_release.txt
doc/internal/index.txt
doc/internal/metadocumentation.txt
doc/internal/python.txt
doc/internal/release.txt
doc/library/config.txt
doc/library/gradient.txt
doc/library/index.txt
doc/library/printing.txt
doc/library/scan.txt
doc/library/tests.txt
doc/library/typed_list.txt
doc/library/compile/debugmode.txt
doc/library/compile/function.txt
